<?xml version="1.0" encoding="UTF-8"?>
<beans xmlns="http://www.springframework.org/schema/beans"
       xmlns:xsi="http://www.w3.org/2001/XMLSchema-instance"
       xsi:schemaLocation="http://www.springframework.org/schema/beans
                           http://www.springframework.org/schema/beans/spring-beans.xsd">

    <!-- 配置ProjectInfo类 -->
    <bean id="myProjectInfo" class="yizhit.workerlib.timer.SelectQuartzProjectInfo"></bean>
    <!--添加数据到数据库任务-->
    <!-- 配置ProjectInfoDetail -->
    <bean id="springQtzProjectInfofMethod" class="org.springframework.scheduling.quartz.MethodInvokingJobDetailFactoryBean">
        <!-- 指定任务类 -->
        <property name="targetObject" ref="myProjectInfo"></property>
        <!-- 指定任务方法 -->
        <property name="targetMethod" value="batchInsertProjectInfo"></property>
        <property name="concurrent" value="false"/>
    </bean>
    <!-- 配置tirgger触发器 -->
    <bean id="ProjectInfoTrigger1" class="org.springframework.scheduling.quartz.CronTriggerFactoryBean">
        <!-- ProjectInfoDetail -->
        <property name="jobDetail" ref="springQtzProjectInfofMethod"></property>

        <!-- cron表达式，执行时间  每5分钟执行一次 -->
        <property name="cronExpression" value="0 *20 * * * ?"></property>
    </bean>


    <!-- 配置UserInfo类 -->
    <bean id="myAllUserInfo" class="yizhit.workerlib.timer.SelectQuartzAllUserInfo"></bean>
    <!--添加数据到数据库任务-->
    <!-- 配置ProjectInfofDetail -->
    <bean id="springQtzAllUserInfoMethod" class="org.springframework.scheduling.quartz.MethodInvokingJobDetailFactoryBean">
        <!-- 指定任务类 -->
        <property name="targetObject" ref="myAllUserInfo"></property>
        <!-- 指定任务方法 -->
        <property name="targetMethod" value="batchInsertArchivesInfo"></property>
        <property name="concurrent" value="false"/>
    </bean>
    <!-- 配置tirgger触发器 -->
    <bean id="AllUserTrigger2" class="org.springframework.scheduling.quartz.CronTriggerFactoryBean">
        <!-- ProjectInfofDetail -->
        <property name="jobDetail" ref="springQtzAllUserInfoMethod"></property>

        <!-- cron表达式，执行时间  每6分钟执行一次 -->
        <property name="cronExpression" value="0 */20 * * * ?"></property>
    </bean>


    <!-- 配置UserInfoUnit_id类 -->
    <!--<bean id="myAllUserInfoUnitID" class="yizhit.workerlib.timer.SelectQuartzAllUserInfo"></bean>-->
    <!--&lt;!&ndash;添加数据到数据库任务&ndash;&gt;-->
    <!--&lt;!&ndash; 配置UserInfoUnit_idDetail &ndash;&gt;-->
    <!--<bean id="springQtzAllUserInfoUnit_IdMethod" class="org.springframework.scheduling.quartz.MethodInvokingJobDetailFactoryBean">-->
        <!--&lt;!&ndash; 指定任务类 &ndash;&gt;-->
        <!--<property name="targetObject" ref="myAllUserInfoUnitID"></property>-->
        <!--&lt;!&ndash; 指定任务方法 &ndash;&gt;-->
        <!--<property name="targetMethod" value="updateAllUserUnitID"></property>-->
    <!--</bean>-->
    <!--&lt;!&ndash; 配置tirgger触发器 &ndash;&gt;-->
    <!--<bean id="cronTrigger6" class="org.springframework.scheduling.quartz.CronTriggerFactoryBean">-->
        <!--&lt;!&ndash; ProjectInfofDetail &ndash;&gt;-->
        <!--<property name="jobDetail" ref="springQtzAllUserInfoUnit_IdMethod"></property>-->

        <!--&lt;!&ndash; cron表达式，执行时间  每9分钟执行一次 &ndash;&gt;-->
        <!--<property name="cronExpression" value="0 */9 * * ?"></property>-->
    <!--</bean>-->


    <!-- 配置UnitInfo类 -->
    <!--<bean id="myUnitInfo" class="yizhit.workerlib.timer.SelectQuartzUnitrInfo"></bean>-->
    <!--添加数据到数据库任务-->
    <!-- 配置ProjectInfofDetail -->
    <!--<bean id="springQtzUnitInfoMethod" class="org.springframework.scheduling.quartz.MethodInvokingJobDetailFactoryBean">-->
        <!--&lt;!&ndash; 指定任务类 &ndash;&gt;-->
        <!--<property name="targetObject" ref="myUnitInfo"></property>-->
        <!--&lt;!&ndash; 指定任务方法 &ndash;&gt;-->
        <!--<property name="targetMethod" value="batchInsertUnitrInfo"></property>-->
    <!--</bean>-->
    <!-- 配置tirgger触发器 -->
    <!--<bean id="cronTrigger3" class="org.springframework.scheduling.quartz.CronTriggerFactoryBean">-->
        <!--&lt;!&ndash; UnitInfofDetail &ndash;&gt;-->
        <!--<property name="jobDetail" ref="springQtzUnitInfoMethod"></property>-->

        <!--&lt;!&ndash; cron表达式，执行时间  每5分钟执行一次 &ndash;&gt;-->
        <!--<property name="cronExpression" value="0 */5 * * * ?"></property>-->
    <!--</bean>-->



    <!-- 配置myArvhivesInfo类 -->
    <bean id="myArvhivesInfo" class="yizhit.workerlib.timer.SelectQuartzArvhivesInfo"></bean>
    <!--添加数据到数据库任务-->
    <!-- 配置myArvhivesInfofDetail -->
    <bean id="springQtzmyArvhivesInfoMethod" class="org.springframework.scheduling.quartz.MethodInvokingJobDetailFactoryBean">
        <!-- 指定任务类 -->
        <property name="targetObject" ref="myArvhivesInfo"></property>
        <!-- 指定任务方法 -->
        <!--<property name="targetMethod" value="batchInsertArvhivesInfo"></property>-->
        <property name="targetMethod" value="batchInsertArvhivesInfo"></property>
        <property name="concurrent" value="false"/>
    </bean>
    <!-- 配置tirgger触发器 -->
    <bean id="ArvhivesTrigger3" class="org.springframework.scheduling.quartz.CronTriggerFactoryBean">
        <!-- ArvhivesInfoDetail -->
        <property name="jobDetail" ref="springQtzmyArvhivesInfoMethod"></property>

        <!-- cron表达式，执行时间  每1小时执行一次 -->
        <property name="cronExpression" value="0 */20 * * * ?"></property>
    </bean>



    <!-- 配置myArvhivesInfoPhoto类 -->
    <bean id="myArvhivesInfoPhoto" class="yizhit.workerlib.timer.SelectQuartzArvhivesInfo"></bean>
    <!--添加数据到数据库任务-->
    <!-- 配置myArvhivesInfoPhotoDetail -->
    <bean id="springQtzmyArvhivesInfoPhotoMethod" class="org.springframework.scheduling.quartz.MethodInvokingJobDetailFactoryBean">
        <!-- 指定任务类 -->
        <property name="targetObject" ref="myArvhivesInfoPhoto"></property>
        <!-- 指定任务方法 -->
        <property name="targetMethod" value="updateArchivesPhoto"></property>
        <property name="concurrent" value="false"/>
    </bean>
    <!-- 配置tirgger触发器 -->
    <bean id="ArvhivesPhotoTrigger4" class="org.springframework.scheduling.quartz.CronTriggerFactoryBean">
        <!-- ArvhivesInfoPhotoDetail -->
        <property name="jobDetail" ref="springQtzmyArvhivesInfoPhotoMethod"></property>

        <!-- cron表达式，执行时间  每10分钟执行一次 -->
        <property name="cronExpression" value="0 */20 * * * ?"></property>
    </bean>


    <!-- 配置myArvhivesInfo类 -->
    <bean id="myCheckWorkceInfo" class="yizhit.workerlib.timer.SelectQuartzCheckWorkceInfo"></bean>
    <!--添加数据到数据库任务-->
    <!-- 配置myArvhivesInfoPhotoDetail -->
    <bean id="springQtzmyCheckWorkceInfoMethod" class="org.springframework.scheduling.quartz.MethodInvokingJobDetailFactoryBean">
        <!-- 指定任务类 -->
        <property name="targetObject" ref="myCheckWorkceInfo"></property>
        <!-- 指定任务方法 -->
        <property name="targetMethod" value="batchInsertCheckWorkceInfo"></property>
        <property name="concurrent" value="false"/>
    </bean>
    <!-- 配置tirgger触发器 -->
    <bean id="CheckWorkceTrigger5" class="org.springframework.scheduling.quartz.CronTriggerFactoryBean">
        <!-- ArvhivesInfoPhotoDetail -->
        <property name="jobDetail" ref="springQtzmyCheckWorkceInfoMethod"></property>

        <!-- cron表达式，执行时间  每10分钟执行一次 -->
        <property name="cronExpression" value="0 */20 * * * ?"></property>
    </bean>




    <!-- 启动定时器 -->
    <bean id="springJobSchedulerFactoryBean" class="org.springframework.scheduling.quartz.SchedulerFactoryBean">
        <property name="triggers">
            <list>
                 <!--此处指的是上面定时的方法-->
                <ref bean="ProjectInfoTrigger1"></ref>
                <ref bean="ArvhivesTrigger3"></ref>
                <ref bean="ArvhivesPhotoTrigger4"></ref>
                <ref bean="AllUserTrigger2"></ref>
<!--                <ref bean="CheckWorkceTrigger5"></ref>-->
            </list>
        </property>

    </bean>
</beans>
